djstripe/__init__.py
djstripe/admin/__init__.py
djstripe/admin/actions.py
djstripe/admin/admin.py
djstripe/admin/admin_inline.py
djstripe/admin/forms.py
djstripe/admin/utils.py
djstripe/admin/views.py
djstripe/apps.py
djstripe/checks.py
djstripe/enums.py
djstripe/event_handlers.py
djstripe/exceptions.py
djstripe/fields.py
djstripe/locale/fr/LC_MESSAGES/django.po
djstripe/locale/ru/LC_MESSAGES/django.po
djstripe/management/__init__.py
djstripe/management/commands/__init__.py
djstripe/management/commands/djstripe_clear_expired_idempotency_keys.py
djstripe/management/commands/djstripe_init_customers.py
djstripe/management/commands/djstripe_process_events.py
djstripe/management/commands/djstripe_sync_customers.py
djstripe/management/commands/djstripe_sync_models.py
djstripe/management/commands/djstripe_update_invoiceitem_ids.py
djstripe/management/commands/stripe_listen.py
djstripe/managers.py
djstripe/migrations/0001_initial.py
djstripe/migrations/0002_2_10.py
djstripe/migrations/__init__.py
djstripe/mixins.py
djstripe/models/__init__.py
djstripe/models/account.py
djstripe/models/api.py
djstripe/models/base.py
djstripe/models/billing.py
djstripe/models/checkout.py
djstripe/models/connect.py
djstripe/models/core.py
djstripe/models/entitlements.py
djstripe/models/identity.py
djstripe/models/issuing.py
djstripe/models/payment_methods.py
djstripe/models/pricing_table.py
djstripe/models/radar.py
djstripe/models/sigma.py
djstripe/models/webhooks.py
djstripe/settings.py
djstripe/signals.py
djstripe/sync.py
djstripe/templates/djstripe/admin/add_form.html
djstripe/templates/djstripe/admin/change_form.html
djstripe/templates/djstripe/admin/confirm_action.html
djstripe/templates/djstripe/admin/webhook_endpoint/add_form.html
djstripe/templates/djstripe/admin/webhook_endpoint/change_form.html
djstripe/templates/djstripe/admin/webhook_endpoint/delete_confirmation.html
djstripe/urls.py
djstripe/utils.py
djstripe/views.py
dj_stripe-2.10.2.dist-info/METADATA
dj_stripe-2.10.2.dist-info/WHEEL
dj_stripe-2.10.2.dist-info/licenses/LICENSE
dj_stripe-2.10.2.dist-info/RECORD
