Metadata-Version: 2.4
Name: dj-stripe
Version: 2.10.2
Summary: Django + Stripe made easy
License: MIT
License-File: LICENSE
Author: Alexander Kavanaugh
Author-email: alex@kavdev.io
Requires-Python: >=3.11,<4.0
Classifier: Development Status :: 5 - Production/Stable
Classifier: Environment :: Web Environment
Classifier: Framework :: Django
Classifier: Framework :: Django :: 5.0
Classifier: Framework :: Django :: 5.1
Classifier: Intended Audience :: Developers
Classifier: License :: OSI Approved :: MIT License
Classifier: Programming Language :: Python :: 3
Classifier: Programming Language :: Python :: 3.11
Classifier: Programming Language :: Python :: 3.12
Classifier: Programming Language :: Python :: 3.13
Classifier: Programming Language :: Python :: 3.14
Classifier: Topic :: Office/Business :: Financial
Classifier: Topic :: Software Development :: Libraries :: Python Modules
Provides-Extra: mysql
Provides-Extra: postgres
Requires-Dist: django (>=5.0)
Requires-Dist: mysqlclient (>=1.4.0) ; extra == "mysql"
Requires-Dist: psycopg (>=3.2.3,<4.0.0) ; extra == "postgres"
Requires-Dist: stripe (>=11.3.0)
Project-URL: Documentation, https://dj-stripe.dev/dj-stripe/
Project-URL: Funding, https://github.com/sponsors/dj-stripe
Project-URL: Homepage, https://dj-stripe.dev
Project-URL: Repository, https://github.com/dj-stripe/dj-stripe
